LICENSE
MANIFEST.in
README.md
setup.py
lodes_star/__init__.py
lodes_star/fetch.py
lodes_star/geographies.csv
lodes_star/sparse_lodes.py
lodes_star/state_codes.py
lodes_star/states.csv
lodes_star/utils.py
lodes_star.egg-info/PKG-INFO
lodes_star.egg-info/SOURCES.txt
lodes_star.egg-info/dependency_links.txt
lodes_star.egg-info/requires.txt
lodes_star.egg-info/top_level.txt