Metadata-Version: 2.1
Name: lodes-star
Version: 0.2.6
Summary: For scraping Longitudinal Origin-Destination Employment Statistics (LODES) data from the US Census as well as fetching Census Block GIS shapefiles.
Home-page: https://github.com/nick-fournier/lodes-star
Author: Nicholas Fournier
Author-email: nichfournier@gmail.com
License: GNU
Platform: UNKNOWN
Classifier: Development Status :: 1 - Planning
Classifier: Intended Audience :: Science/Research
Classifier: Programming Language :: Python :: 3.9
License-File: LICENSE
